git_commit_ai/__init__.py
git_commit_ai/cli.py
git_commit_ai/git_utils.py
git_commit_ai/llm.py
git_commit_ai/main.py
git_commit_ai/models.py
git_commit_ai/prompts.py
ai_git_commit_gen-0.1.2.dist-info/METADATA
ai_git_commit_gen-0.1.2.dist-info/WHEEL
ai_git_commit_gen-0.1.2.dist-info/entry_points.txt
ai_git_commit_gen-0.1.2.dist-info/licenses/LICENSE
ai_git_commit_gen-0.1.2.dist-info/RECORD
