Metadata-Version: 2.4
Name: ai-git-commit-gen
Version: 0.1.2
Summary: AI-powered git commit message generator
Project-URL: Homepage, https://github.com/yogichoudhari/ai-git-commit-gen
Project-URL: Repository, https://github.com/yogichoudhari/ai-git-commit-gen
Project-URL: Issues, https://github.com/yogichoudhari/ai-git-commit-gen/issues
Author-email: Yogesh Choudhari <yogigurjar73542@gmail.com>
License-Expression: MIT
License-File: LICENSE
Keywords: ai,cli,commit,developer-tools,git
Classifier: Development Status :: 4 - Beta
Classifier: Environment :: Console
Classifier: Intended Audience :: Developers
Classifier: License :: OSI Approved :: MIT License
Classifier: Programming Language :: Python :: 3.9
Classifier: Programming Language :: Python :: 3.10
Classifier: Programming Language :: Python :: 3.11
Classifier: Programming Language :: Python :: 3.12
Classifier: Topic :: Software Development :: Version Control :: Git
Requires-Python: >=3.9
Requires-Dist: gitpython>=3.1.0
Requires-Dist: httpx>=0.25.0
Requires-Dist: pydantic>=2.0.0
Requires-Dist: rich>=13.0.0
Requires-Dist: typer>=0.9.0
